kerb_sts/__init__.py
kerb_sts/__main__.py
kerb_sts/auth.py
kerb_sts/awsrole.py
kerb_sts/config.py
kerb_sts/handler.py
tests/__init__.py
tests/test_awsrole.py
kerb_sts-0.1.13.dist-info/LICENSE.md
kerb_sts-0.1.13.dist-info/METADATA
kerb_sts-0.1.13.dist-info/WHEEL
kerb_sts-0.1.13.dist-info/entry_points.txt
kerb_sts-0.1.13.dist-info/top_level.txt
kerb_sts-0.1.13.dist-info/RECORD
