Metadata-Version: 2.1
Name: kerb-sts
Version: 0.1.13
Summary: Renew AWS Simple Token Service Credentials
Home-page: https://github.com/commercehub-oss/kerb-sts.git
Author: CommerceHub
License: UNKNOWN
Platform: UNKNOWN
Classifier: Programming Language :: Python :: 2.7
Classifier: Programming Language :: Python :: 3.4
Classifier: Programming Language :: Python :: 3.5
Requires-Dist: beautifulsoup4 (>=4.4.1)
Requires-Dist: boto (>=2.43.0)
Requires-Dist: boto3 (>=1.4.2)
Requires-Dist: botocore (>=1.4.80)
Requires-Dist: configparser (==3.5.0)
Requires-Dist: ntlm-auth (==1.0.2)
Requires-Dist: requests (>=2.12.3)
Requires-Dist: requests-kerberos (>=0.11.0)
Requires-Dist: requests-ntlm (>=0.3.0)
Requires-Dist: six (>=1.10.0)
Requires-Dist: pexpect (>=4.0.0)
